siga_mcp/__init__.py
siga_mcp/_types.py
siga_mcp/clients.py
siga_mcp/constants.py
siga_mcp/decorators.py
siga_mcp/domain.py
siga_mcp/dynamic_constants.py
siga_mcp/main.py
siga_mcp/memory.py
siga_mcp/prompt.py
siga_mcp/protocols.py
siga_mcp/test.py
siga_mcp/utils.py
siga_mcp/xml_builder.py
siga_mcp/docstrings/__version__.py
siga_mcp/docstrings/alterar_status_os_siga_ia.py
siga_mcp/docstrings/atualizar_horarios_colaborador.py
siga_mcp/docstrings/atualizar_tempo_gasto_atendimento.py
siga_mcp/docstrings/buscar_informacoes_atendimento_avulso.py
siga_mcp/docstrings/buscar_informacoes_atendimentos_os.py
siga_mcp/docstrings/buscar_informacoes_os.py
siga_mcp/docstrings/buscar_instrucoes_de_uso_siga.py
siga_mcp/docstrings/buscar_pendencias_lancamentos_atendimentos.py
siga_mcp/docstrings/buscar_pendencias_multiplas_matriculas.py
siga_mcp/docstrings/buscar_todas_os_usuario.py
siga_mcp/docstrings/cancelar_os_siga_ia.py
siga_mcp/docstrings/colaboradores_ativos_siga.py
siga_mcp/docstrings/concluir_os_siga_ia.py
siga_mcp/docstrings/editar_atendimento_avulso_infraestrutura.py
siga_mcp/docstrings/editar_atendimento_avulso_sistemas.py
siga_mcp/docstrings/editar_atendimentos_os.py
siga_mcp/docstrings/editar_os_infraestrutura.py
siga_mcp/docstrings/editar_os_sistemas.py
siga_mcp/docstrings/excluir_atendimento_avulso.py
siga_mcp/docstrings/excluir_atendimentos_os.py
siga_mcp/docstrings/extrair_matriculas_do_xml.py
siga_mcp/docstrings/inserir_atendimento_avulso_infraestrutura.py
siga_mcp/docstrings/inserir_atendimento_avulso_sistemas.py
siga_mcp/docstrings/inserir_atendimentos_os.py
siga_mcp/docstrings/inserir_os_infraestrutura.py
siga_mcp/docstrings/inserir_os_sistemas.py
siga_mcp/docstrings/listar_atendimentos_avulsos.py
siga_mcp/docstrings/listar_atendimentos_os.py
siga_mcp/docstrings/listar_horas_trabalhadas.py
siga_mcp/docstrings/listar_usuarios_equipe_por_gerente.py
siga_mcp/docstrings/listar_usuarios_responsaveis_os_siga.py
siga_mcp/tools/__init__.py
siga_mcp-0.1.77.dist-info/METADATA
siga_mcp-0.1.77.dist-info/WHEEL
siga_mcp-0.1.77.dist-info/entry_points.txt
siga_mcp-0.1.77.dist-info/RECORD
