Metadata-Version: 2.4
Name: siga-mcp
Version: 0.1.77
Summary: Add your description here
Requires-Python: >=3.13
Requires-Dist: aiohttp>=3.12.15
Requires-Dist: dateparser>=1.2.2
Requires-Dist: fastmcp>=2.11.1
Requires-Dist: langfuse>=3.3.5
Requires-Dist: msgraph-sdk>=1.45.0
Requires-Dist: rock-solid-base>=0.1.11
Requires-Dist: ujson>=5.10.0
